yalab_procedures/__init__.py
yalab_procedures/cli.py
yalab_procedures/yalab_procedures.py
yalab_procedures-0.0.1.dist-info/AUTHORS.rst
yalab_procedures-0.0.1.dist-info/LICENSE
yalab_procedures-0.0.1.dist-info/METADATA
yalab_procedures-0.0.1.dist-info/WHEEL
yalab_procedures-0.0.1.dist-info/entry_points.txt
yalab_procedures-0.0.1.dist-info/RECORD
