Metadata-Version: 2.1
Name: yalab_procedures
Version: 0.0.1
Summary: The yalab-procedures repository is dedicated to managing and executing data processing procedures for MRI data in the Assaf Neuro Lab.
Home-page: https://github.com/yalab-dev/yalab_procedures
License: MIT
Keywords: neuroscience,MRI,data processing,automation,standardization
Author: YALab DevOps
Author-email: yalab.dev@gmail.com
Requires-Python: >=3.10,<4.0
Classifier: Development Status :: 3 - Alpha
Classifier: Intended Audience :: Science/Research
Classifier: License :: OSI Approved :: MIT License
Classifier: Programming Language :: Python :: 3
Classifier: Programming Language :: Python :: 3.10
Classifier: Programming Language :: Python :: 3.11
Classifier: Programming Language :: Python :: 3.12
Classifier: Topic :: Scientific/Engineering :: Information Analysis
Requires-Dist: bump2version (>=1.0.1,<2.0.0)
Requires-Dist: chardet (>=5.2.0,<6.0.0)
Requires-Dist: ipykernel (>=6.29.4,<7.0.0)
Requires-Dist: pre-commit (>=3.7.1,<4.0.0)
Requires-Dist: sphinx (>=7.3.7,<8.0.0)
Requires-Dist: sphinx-rtd-theme (>=2.0.0,<3.0.0)
Requires-Dist: tox (>=4.15.0,<5.0.0)
Requires-Dist: twine (>=5.1.0,<6.0.0)
Requires-Dist: typer (>=0.12.0,<0.13.0)
Requires-Dist: wheel (>=0.43.0,<0.44.0)
Project-URL: Documentation, https://github.com/yalab-dev/yalab_procedures
Project-URL: Repository, https://github.com/yalab-dev/yalab_procedures
